magnetic_field_calculator/__init__.py
magnetic_field_calculator/__main__.py
magnetic_field_calculator-1.0.2.dist-info/LICENSE
magnetic_field_calculator-1.0.2.dist-info/METADATA
magnetic_field_calculator-1.0.2.dist-info/WHEEL
magnetic_field_calculator-1.0.2.dist-info/entry_points.txt
magnetic_field_calculator-1.0.2.dist-info/top_level.txt
magnetic_field_calculator-1.0.2.dist-info/RECORD
