Metadata-Version: 2.1
Name: magnetic-field-calculator
Version: 1.0.2
Summary: Python API for British Geological Survey magnetic field calculator
Home-page: https://github.com/filips123/MagneticFieldCalculator/
Author: Filip Š
Author-email: projects@filips.si
License: GPLv3+
Keywords: british-geological-survey,geomag,magnetic-field,api,calculator
Platform: UNKNOWN
Classifier: Development Status :: 5 - Production/Stable
Classifier: Intended Audience :: Education
Classifier: Intended Audience :: Science/Research
Classifier: License :: OSI Approved :: GNU General Public License v3 or later (GPLv3+)
Classifier: Programming Language :: Python :: 3
Classifier: Topic :: Scientific/Engineering :: Atmospheric Science
Classifier: Topic :: Scientific/Engineering :: Physics
Requires-Python: >= 3.4
Provides-Extra: lint
